[
    {
    "timestamp":"2022-10-07 12:54:00",
    "deviceName":"LuxSensor",
    "deviceId":"01MIS55C",
    "deviceType":"Light-Sensor",
    "gatewayName":"PRGW-XXX",
    "location":"device-location",
    "dBm":"-80",
    "security":"No",
    "illumination":{
       "value":544,
       "unit":"lx"
        },
    "supplyVoltage":{
       "value":2.72,
       "unit":"V"
        }
    },
    {
        "timestamp":"2022-10-07 12:54:10",
        "deviceName":"LuxSensor",
        "deviceId":"01MIS55C",
        "deviceType":"Light-Sensor",
        "gatewayName":"PRGW-XXX",
        "location":"device-location",
        "dBm":"-80",
        "security":"No",
        "illumination":{
           "value":544,
           "unit":"lx"
            },
        "supplyVoltage":{
           "value":2.72,
           "unit":"V"
            }
    },
    {
        "timestamp":"2022-10-07 12:54:20",
        "deviceName":"LuxSensor",
        "deviceId":"01MIS55C",
        "deviceType":"Light-Sensor",
        "gatewayName":"PRGW-XXX",
        "location":"device-location",
        "dBm":"-80",
        "security":"No",
        "illumination":{
           "value":544,
           "unit":"lx"
            },
        "supplyVoltage":{
           "value":2.72,
           "unit":"V"
            }
    },
    {
        "timestamp":"2022-10-07 12:54:30",
        "deviceName":"LuxSensor",
        "deviceId":"01MIS55C",
        "deviceType":"Light-Sensor",
        "gatewayName":"PRGW-XXX",
        "location":"device-location",
        "dBm":"-80",
        "security":"No",
        "illumination":{
           "value":544,
           "unit":"lx"
            },
        "supplyVoltage":{
           "value":2.72,
           "unit":"V"
            }
    },
    {
        "timestamp":"2022-10-07 12:54:40",
        "deviceName":"LuxSensor",
        "deviceId":"01MIS55C",
        "deviceType":"Light-Sensor",
        "gatewayName":"PRGW-XXX",
        "location":"device-location",
        "dBm":"-80",
        "security":"No",
        "illumination":{
           "value":544,
           "unit":"lx"
            },
        "supplyVoltage":{
           "value":2.72,
           "unit":"V"
            }
    },
    {
        "timestamp":"2022-10-07 12:54:50",
        "deviceName":"LuxSensor",
        "deviceId":"01MIS55C",
        "deviceType":"Light-Sensor",
        "gatewayName":"PRGW-XXX",
        "location":"device-location",
        "dBm":"-80",
        "security":"No",
        "illumination":{
           "value":544,
           "unit":"lx"
            },
        "supplyVoltage":{
           "value":2.72,
           "unit":"V"
            }
    }
    
] 